palantir_oauth_client/__init__.py
palantir_oauth_client/_client.py
palantir_oauth_client/_flow.py
palantir_oauth_client/_utils.py
palantir_oauth_client/_version.py
palantir_oauth_client/_webserver.py
palantir_oauth_client/auth.py
palantir_oauth_client/cache.py
palantir_oauth_client/credentials.py
palantir_oauth_client/errors.py
palantir_oauth_client-1.6.1.dist-info/LICENSE
palantir_oauth_client-1.6.1.dist-info/WHEEL
palantir_oauth_client-1.6.1.dist-info/METADATA
palantir_oauth_client-1.6.1.dist-info/RECORD
