Metadata-Version: 2.1
Name: palantir-oauth-client
Version: 1.6.1
Summary: OAuth2 client for Palantir Foundry
Home-page: https://github.com/palantir/palantir-oauth-client
License: Apache-2.0
Author: Thomas Powell
Author-email: tpowell@palantir.com
Requires-Python: >=3.8,<4.0
Classifier: License :: OSI Approved :: Apache Software License
Classifier: Programming Language :: Python :: 3
Classifier: Programming Language :: Python :: 3.10
Classifier: Programming Language :: Python :: 3.8
Classifier: Programming Language :: Python :: 3.9
Requires-Dist: oauthlib (>=3.2.2)
Requires-Dist: requests (>=2.28.2)
Requires-Dist: requests-oauthlib (>=1.3.1)
